NiceGUIExtAPI/TListBoxAPI.py
NiceGUIExtAPI/__init__.py
niceguiextapi-0.0.1.dist-info/licenses/LICENSE
niceguiextapi-0.0.1.dist-info/METADATA
niceguiextapi-0.0.1.dist-info/WHEEL
niceguiextapi-0.0.1.dist-info/top_level.txt
niceguiextapi-0.0.1.dist-info/RECORD
