Metadata-Version: 2.4
Name: NiceGUIExtAPI
Version: 0.0.1
Summary: NiceGUIExtAPI Python package
Author-email: James Lin <tylin123@ms27.hinet.net>
License: Copyright (c) 2025 James Lin
Project-URL: Homepage, https://mis.gotech.biz
License-File: LICENSE
Dynamic: license-file
